lirpy/__init__.py
lirpy/__main__.py
lirpy/mask.py
lirpy/point.py
lirpy/rect.py
lirpy/rectangulator.py
lirpy-0.0.1.dist-info/METADATA
lirpy-0.0.1.dist-info/WHEEL
lirpy-0.0.1.dist-info/RECORD
