Metadata-Version: 2.1
Name: lirpy
Version: 0.0.1
Summary: 
Author: Rob Nelson
Author-email: nexisentertainment@gmail.com
Requires-Python: >=3.10,<4.0
Classifier: Programming Language :: Python :: 3
Classifier: Programming Language :: Python :: 3.10
Classifier: Programming Language :: Python :: 3.11
